{"": {"S2_Class_CarInfo": {"pic": ["./Project/Img/KoenigseggJesko.png", "./Project/Img/MercedesAMGOne.png", "./Project/Img/HennesseyVenomF5.png", "./Project/Img/LamborghiniSestoElemento.png"], "name": ["Koenigsegg Jesko", "Mercedes AMG One", "Hennessey Venom F5", "Lamborghini Sesto Elemento"], "price": ["2,800,000 CR", "2,700,000 CR", "3,000,000 CR", "2,500,000 CR"], "engine": ["5.0L Twin-Turbocharged V8\n                                  1280 bhp (954 kW), 883 lb\u22c5ft (1197 N\u00b7m)", "1.6L Turbocharged Hybrid V6\n877 bhp (654 kW), 535 lb\u22c5ft (725 N\u00b7m)", "6.6L Twin-Turbocharged V8\n1817 bhp (1355 kW), 1193 lb\u22c5ft (1617 N\u00b7m)", "5.2L Naturally-Aspirated V10\n571 bhp (426 kW), 398 lb\u22c5ft (540 N\u00b7m)"], "layout": ["Mid-Engined, Rear-Wheel Drive\n9-speed Transmission", "Mid-Engined, All-Wheel Drive\n8-speed Transmission", "Mid-Engined, Rear-Wheel Drive\n7-speed Transmission", "Mid-Engined, All-Wheel Drive\n6-speed Transmission"], "weight": ["3131 lbs (1420 kg)", "3737 lbs (1695 kg)", "3053 lbs (1385 kg)", "2202 lbs (999 kg)"]}, "S1_Class_CarInfo": {"pic": ["./Project/Img/PorscheCarreraGT.png", "./Project/Img/McLaren720SSpider.png", "./Project/Img/FerrariEnzo.png", "./Project/Img/BugattiEB110.png"], "name": ["Porsche Carrera GT", "McLaren 720S Spider", "Ferrari Enzo", "Bugatti EB110"], "price": ["1,000,000 CR", "340,000 CR", "2,800,000 CR", "1,700,000 CR"], "engine": ["5.0L Twin-Turbocharged V8\n                                  1280 bhp (954 kW), 883 lb\u22c5ft (1197 N\u00b7m)", "1.6L Turbocharged Hybrid V6\n877 bhp (654 kW), 535 lb\u22c5ft (725 N\u00b7m)", "6.6L Twin-Turbocharged V8\n1817 bhp (1355 kW), 1193 lb\u22c5ft (1617 N\u00b7m)", "5.2L Naturally-Aspirated V10\n571 bhp (426 kW), 398 lb\u22c5ft (540 N\u00b7m)"], "layout": ["Mid-Engined, Rear-Wheel Drive\n9-speed Transmission", "Mid-Engined, All-Wheel Drive\n8-speed Transmission", "Mid-Engined, Rear-Wheel Drive\n7-speed Transmission", "Mid-Engined, All-Wheel Drive\n6-speed Transmission"], "weight": ["3131 lbs (1420 kg)", "3737 lbs (1695 kg)", "3053 lbs (1385 kg)", "2202 lbs (999 kg)"]}, "A_Class_CarInfo": {"pic": ["./Project/Img/LamborghiniCountach.png", "./Project/Img/Porsche911GT2.png", "./Project/Img/ToyotaSupraRZ.png", "./Project/Img/Mercedes-BenzE63AMG.png"], "name": ["Lamborghini Countach", "Porsche 911 GT2", "Toyota Supra RZ", "Mercedes-Benz E63 AMG"], "price": ["220,000 CR", "550,000 CR", "38,000 CR", "105,000 CR"], "engine": ["5.0L Twin-Turbocharged V8\n                                  1280 bhp (954 kW), 883 lb\u22c5ft (1197 N\u00b7m)", "1.6L Turbocharged Hybrid V6\n877 bhp (654 kW), 535 lb\u22c5ft (725 N\u00b7m)", "6.6L Twin-Turbocharged V8\n1817 bhp (1355 kW), 1193 lb\u22c5ft (1617 N\u00b7m)", "5.2L Naturally-Aspirated V10\n571 bhp (426 kW), 398 lb\u22c5ft (540 N\u00b7m)"], "layout": ["Mid-Engined, Rear-Wheel Drive\n9-speed Transmission", "Mid-Engined, All-Wheel Drive\n8-speed Transmission", "Mid-Engined, Rear-Wheel Drive\n7-speed Transmission", "Mid-Engined, All-Wheel Drive\n6-speed Transmission"], "weight": ["3131 lbs (1420 kg)", "3737 lbs (1695 kg)", "3053 lbs (1385 kg)", "2202 lbs (999 kg)"]}, "Eco_Friendly_CarInfo": {"pic": ["./Project/Img/LotusEvija.png", "./Project/Img/RimacConceptTwo.png", "./Project/Img/PorscheTaycanTurboS.png", "./Project/Img/FordMustangMachE1400.png"], "name": ["Koenigsegg Jesko", "Mercedes AMG One", "Hennessey Venom F5", "Lamborghini Sesto Elemento"], "price": ["2,800,000 CR", "2,700,000 CR", "3,000,000 CR", "2,500,000 CR"], "engine": ["5.0L Twin-Turbocharged V8\n                                  1280 bhp (954 kW), 883 lb\u22c5ft (1197 N\u00b7m)", "1.6L Turbocharged Hybrid V6\n877 bhp (654 kW), 535 lb\u22c5ft (725 N\u00b7m)", "6.6L Twin-Turbocharged V8\n1817 bhp (1355 kW), 1193 lb\u22c5ft (1617 N\u00b7m)", "5.2L Naturally-Aspirated V10\n571 bhp (426 kW), 398 lb\u22c5ft (540 N\u00b7m)"], "layout": ["Mid-Engined, Rear-Wheel Drive\n9-speed Transmission", "Mid-Engined, All-Wheel Drive\n8-speed Transmission", "Mid-Engined, Rear-Wheel Drive\n7-speed Transmission", "Mid-Engined, All-Wheel Drive\n6-speed Transmission"], "weight": ["3131 lbs (1420 kg)", "3737 lbs (1695 kg)", "3053 lbs (1385 kg)", "2202 lbs (999 kg)"]}, "S2_Class": {"banner": ["./Project/Img/S2 Class.png"], "pic": ["./Project/Img/KoenigseggJesko.png", "./Project/Img/MercedesAMGOne.png", "./Project/Img/HennesseyVenomF5.png", "./Project/Img/LamborghiniSestoElemento.png"], "name": ["Koenigsegg Jesko", "Mercedes AMG One", "Hennessey Venom F5", "Lamborghini Sesto Elemento"], "price": ["2,800,000 CR", "2,700,000 CR", "3,000,000 CR", "2,500,000 CR"], "priceNumber": [0, 0, 0, 0]}, "S1_Class": {"banner": ["./Project/Img/S1 Class.png"], "pic": ["./Project/Img/PorscheCarreraGT.png", "./Project/Img/McLaren720SSpider.png", "./Project/Img/FerrariEnzo.png", "./Project/Img/BugattiEB110.png"], "name": ["Porsche Carrera GT", "McLaren 720S Spider", "Ferrari Enzo", "Bugatti EB110"], "price": ["1,000,000 CR", "340,000 CR", "2,800,000 CR", "1,700,000 CR"], "priceNumber": [0, 0, 0, 0]}, "A_Class": {"banner": ["./Project/Img/A Class.png"], "pic": ["./Project/Img/LamborghiniCountach.png", "./Project/Img/Porsche911GT2.png", "./Project/Img/ToyotaSupraRZ.png", "./Project/Img/Mercedes-BenzE63AMG.png"], "name": ["Lamborghini Countach", "Porsche 911 GT2", "Toyota Supra RZ", "Mercedes-Benz E63 AMG"], "price": ["220,000 CR", "550,000 CR", "38,000 CR", "105,000 CR"], "priceNumber": [0, 0, 0, 0]}, "Eco_Friendly": {"banner": ["./Project/Img/Eco-Friendly.png"], "pic": ["./Project/Img/LotusEvija.png", "./Project/Img/RimacConceptTwo.png", "./Project/Img/PorscheTaycanTurboS.png", "./Project/Img/FordMustangMachE1400.png"], "name": ["Lotus Evija", "Rimac Concept Two", "Porsche Taycan Turbo S", "Ford Mustang Mach-E 1400"], "price": ["2,500,000 CR", "2,000,000 CR", "185,000 CR", "750,000 CR"], "priceNumber": [0, 0, 0, 0]}}}